py4AxisStage/__init__.py
py4AxisStage/py4AxisStage.py
py4AxisStage-0.0.3.dist-info/METADATA
py4AxisStage-0.0.3.dist-info/WHEEL
py4AxisStage-0.0.3.dist-info/top_level.txt
py4AxisStage-0.0.3.dist-info/RECORD
